bayescalc/__init__.py
bayescalc/batch.py
bayescalc/commands.py
bayescalc/completer.py
bayescalc/expression_parser.py
bayescalc/inference.py
bayescalc/lexer.py
bayescalc/main.py
bayescalc/network_model.py
bayescalc/parser.py
bayescalc/queries.py
bayescalc/repl.py
bayescalc/visualizer.py
bayescalc2-1.0.3.dist-info/licenses/LICENSE
bayescalc2-1.0.3.dist-info/METADATA
bayescalc2-1.0.3.dist-info/WHEEL
bayescalc2-1.0.3.dist-info/entry_points.txt
bayescalc2-1.0.3.dist-info/top_level.txt
bayescalc2-1.0.3.dist-info/RECORD
